webvtt_python/__init__.py
webvtt_python/models.py
webvtt_python/parser.py
webvtt_python-0.2.0.dist-info/METADATA
webvtt_python-0.2.0.dist-info/WHEEL
webvtt_python-0.2.0.dist-info/licenses/LICENSE.md
webvtt_python-0.2.0.dist-info/RECORD
