Metadata-Version: 2.4
Name: webvtt-python
Version: 0.2.0
Summary: Python WebVTT API Implementation
Project-URL: Homepage, https://github.com/BrianMcBrayer/webvtt-python
Project-URL: Repository, https://github.com/BrianMcBrayer/webvtt-python
Project-URL: Issues, https://github.com/BrianMcBrayer/webvtt-python/issues
Author-email: Brian McBrayer <brandmcbrayer@live.com>
License-Expression: MIT
License-File: LICENSE.md
Keywords: captions,subtitles,webvtt
Classifier: Development Status :: 3 - Alpha
Classifier: Intended Audience :: Developers
Classifier: License :: OSI Approved :: MIT License
Classifier: Programming Language :: Python :: 3
Classifier: Programming Language :: Python :: 3.9
Classifier: Programming Language :: Python :: 3.10
Classifier: Programming Language :: Python :: 3.11
Classifier: Programming Language :: Python :: 3.12
Classifier: Programming Language :: Python :: 3.13
Classifier: Topic :: Multimedia :: Video
Classifier: Topic :: Text Processing :: Markup
Requires-Python: <3.14,>=3.9
